controlnet_k/__init__.py
controlnet_k/annotator/canny/__init__.py
controlnet_k/annotator/ckpts/ckpts.txt
controlnet_k/annotator/hed/__init__.py
controlnet_k/annotator/midas/__init__.py
controlnet_k/annotator/midas/api.py
controlnet_k/annotator/midas/midas/__init__.py
controlnet_k/annotator/midas/midas/base_model.py
controlnet_k/annotator/midas/midas/blocks.py
controlnet_k/annotator/midas/midas/dpt_depth.py
controlnet_k/annotator/midas/midas/midas_net.py
controlnet_k/annotator/midas/midas/midas_net_custom.py
controlnet_k/annotator/midas/midas/transforms.py
controlnet_k/annotator/midas/midas/vit.py
controlnet_k/annotator/midas/utils.py
controlnet_k/annotator/mlsd/__init__.py
controlnet_k/annotator/mlsd/models/mbv2_mlsd_large.py
controlnet_k/annotator/mlsd/models/mbv2_mlsd_tiny.py
controlnet_k/annotator/mlsd/utils.py
controlnet_k/annotator/openpose/__init__.py
controlnet_k/annotator/openpose/body.py
controlnet_k/annotator/openpose/hand.py
controlnet_k/annotator/openpose/model.py
controlnet_k/annotator/openpose/util.py
controlnet_k/annotator/uniformer/__init__.py
controlnet_k/annotator/uniformer/configs/_base_/datasets/ade20k.py
controlnet_k/annotator/uniformer/configs/_base_/datasets/chase_db1.py
controlnet_k/annotator/uniformer/configs/_base_/datasets/cityscapes.py
controlnet_k/annotator/uniformer/configs/_base_/datasets/cityscapes_769x769.py
controlnet_k/annotator/uniformer/configs/_base_/datasets/drive.py
controlnet_k/annotator/uniformer/configs/_base_/datasets/hrf.py
controlnet_k/annotator/uniformer/configs/_base_/datasets/pascal_context.py
controlnet_k/annotator/uniformer/configs/_base_/datasets/pascal_context_59.py
controlnet_k/annotator/uniformer/configs/_base_/datasets/pascal_voc12.py
controlnet_k/annotator/uniformer/configs/_base_/datasets/pascal_voc12_aug.py
controlnet_k/annotator/uniformer/configs/_base_/datasets/stare.py
controlnet_k/annotator/uniformer/configs/_base_/default_runtime.py
controlnet_k/annotator/uniformer/configs/_base_/models/ann_r50-d8.py
controlnet_k-0.1.4.dist-info/WHEEL
controlnet_k-0.1.4.dist-info/METADATA
controlnet_k-0.1.4.dist-info/RECORD
