Metadata-Version: 2.1
Name: controlnet-k
Version: 0.1.4
Summary: fork of controlnet model
Author: Fork 
Author-email: hello@fal.ai
Requires-Python: >=3.8,<4.0
Classifier: Programming Language :: Python :: 3
Classifier: Programming Language :: Python :: 3.8
Classifier: Programming Language :: Python :: 3.9
Classifier: Programming Language :: Python :: 3.10
Classifier: Programming Language :: Python :: 3.11
